[{"pid":"1631","uid":"527"},{"pid":"1631","uid":"527"},{"pid":"1631","uid":"527"},{"pid":"1631","uid":"527"},{"pid":"1631","uid":"527"},{"pid":"1631","uid":"527"},{"pid":"1631","uid":"527"},{"pid":"1631","uid":"527"},{"pid":"1631","uid":"527"},{"pid":"1631","uid":"527"},{"pid":"1631","uid":"527"},{"pid":"1631","uid":"527"},{"pid":"1631","uid":"527"},{"pid":"1631","uid":"527"},{"pid":"1631","uid":"527"},{"pid":"1631","uid":"527"},{"pid":"1631","uid":"527"},{"pid":"1631","uid":"527"},{"pid":"1631","uid":"527"},{"pid":"1631","uid":"527"},{"pid":"1631","uid":"527"},{"pid":"1631","uid":"527"},{"pid":"1631","uid":"527"},{"pid":"1631","uid":"527"},{"pid":"1631","uid":"527"},{"pid":"1631","uid":"527"},{"pid":"1631","uid":"527"},{"pid":"1631","uid":"527"},{"pid":"1631","uid":"527"},{"pid":"1631","uid":"527"},{"pid":"1631","uid":"527"},{"pid":"1631","uid":"527"},{"pid":"1631","uid":"527"},{"pid":"1631","uid":"527"},{"pid":"1631","uid":"527"},{"pid":"1631","uid":"527"},{"pid":"1631","uid":"527"},{"pid":"1631","uid":"527"},{"pid":"1631","uid":"527"},{"pid":"1631","uid":"527"},{"pid":"1631","uid":"527"},{"pid":"1631","uid":"527"},{"pid":"1631","uid":"527"},{"pid":"1631","uid":"527"},{"pid":"1631","uid":"527"},{"pid":"1631","uid":"527"},{"pid":"1631","uid":"527"},{"pid":"1631","uid":"527"},{"pid":"1631","uid":"527"},{"pid":"1631","uid":"527"},{"pid":"1631","uid":"527"},{"pid":"1631","uid":"527"},{"pid":"1631","uid":"527"},{"pid":"1631","uid":"527"},{"pid":"1631","uid":"527"},{"pid":"1631","uid":"527"},{"pid":"1631","uid":"527"},{"pid":"1631","uid":"527"},{"pid":"1631","uid":"527"},{"pid":"1631","uid":"527"},{"pid":"1631","uid":"527"},{"pid":"1631","uid":"527"},{"pid":"1631","uid":"527"},{"pid":"1631","uid":"527"},{"pid":"1631","uid":"527"},{"pid":"1631","uid":"527"},{"pid":"1631","uid":"527"},{"pid":"1631","uid":"527"},{"pid":"1631","uid":"527"},{"pid":"1631","uid":"527"},{"pid":"1631","uid":"527"},{"pid":"1631","uid":"527"},{"pid":"1631","uid":"527"},{"pid":"1631","uid":"527"},{"pid":"1631","uid":"527"},{"pid":"1631","uid":"527"},{"pid":"1631","uid":"527"},{"pid":"1631","uid":"527"},{"pid":"1631","uid":"527"},{"pid":"1631","uid":"527"},{"pid":"1631","uid":"527"},{"pid":"1631","uid":"527"},{"pid":"1631","uid":"527"},{"pid":"1631","uid":"527"},{"pid":"1631","uid":"527"},{"pid":"1631","uid":"527"},{"pid":"1631","uid":"527"},{"pid":"1631","uid":"527"},{"pid":"1631","uid":"527"},{"pid":"1631","uid":"527"},{"pid":"1631","uid":"527"},{"pid":"1631","uid":"527"},{"pid":"1631","uid":"527"},{"pid":"1631","uid":"527"},{"pid":"1631","uid":"527"},{"pid":"1631","uid":"527"},{"pid":"1631","uid":"527"},{"pid":"1631","uid":"527"},{"pid":"1631","uid":"527"},{"pid":"1631","uid":"527"},{"pid":"1631","uid":"527"},{"pid":"1631","uid":"527"},{"pid":"1631","uid":"527"},{"pid":"1631","uid":"527"},{"pid":"1631","uid":"527"},{"pid":"1631","uid":"527"},{"pid":"1631","uid":"527"},{"pid":"1631","uid":"527"},{"pid":"1631","uid":"527"},{"pid":"1631","uid":"527"},{"pid":"1631","uid":"527"},{"pid":"1631","uid":"527"},{"pid":"1631","uid":"527"},{"pid":"1631","uid":"527"},{"pid":"1631","uid":"527"},{"pid":"1631","uid":"527"},{"pid":"1631","uid":"527"},{"pid":"1631","uid":"527"},{"pid":"1631","uid":"527"},{"pid":"1631","uid":"527"},{"pid":"1631","uid":"527"},{"pid":"1631","uid":"527"},{"pid":"1631","uid":"527"},{"pid":"1631","uid":"527"},{"pid":"1631","uid":"527"},{"pid":"1631","uid":"527"},{"pid":"1631","uid":"527"},{"pid":"1631","uid":"527"},{"pid":"1631","uid":"527"},{"pid":"1631","uid":"527"},{"pid":"1631","uid":"527"},{"pid":"1631","uid":"527"},{"pid":"1631","uid":"527"},{"pid":"1631","uid":"527"},{"pid":"1631","uid":"527"},{"pid":"1631","uid":"527"},{"pid":"1631","uid":"527"},{"pid":"1631","uid":"527"},{"pid":"1631","uid":"527"},{"pid":"1631","uid":"527"},{"pid":"1631","uid":"527"},{"pid":"1631","uid":"527"},{"pid":"1631","uid":"527"},{"pid":"1631","uid":"527"},{"pid":"1631","uid":"527"},{"pid":"1631","uid":"527"},{"pid":"1631","uid":"527"},{"pid":"1631","uid":"527"},{"pid":"1631","uid":"527"},{"pid":"1631","uid":"527"},{"pid":"1631","uid":"527"},{"pid":"1631","uid":"527"},{"pid":"1631","uid":"527"},{"pid":"1631","uid":"527"},{"pid":"1631","uid":"527"},{"pid":"1631","uid":"527"},{"pid":"1631","uid":"527"},{"pid":"1631","uid":"527"},{"pid":"1631","uid":"527"},{"pid":"1631","uid":"527"},{"pid":"1631","uid":"527"},{"pid":"1631","uid":"527"},{"pid":"1631","uid":"527"},{"pid":"1631","uid":"527"},{"pid":"1631","uid":"527"},{"pid":"1631","uid":"527"},{"pid":"1631","uid":"527"},{"pid":"1631","uid":"527"},{"pid":"1631","uid":"527"},{"pid":"1631","uid":"527"},{"pid":"1631","uid":"527"},{"pid":"1631","uid":"527"},{"pid":"1631","uid":"527"},{"pid":"1631","uid":"527"},{"pid":"1631","uid":"527"},{"pid":"1631","uid":"527"},{"pid":"1631","uid":"527"},{"pid":"1631","uid":"527"},{"pid":"1631","uid":"527"},{"pid":"1631","uid":"527"},{"pid":"1631","uid":"527"},{"pid":"1631","uid":"527"},{"pid":"1631","uid":"527"},{"pid":"1631","uid":"527"},{"pid":"1631","uid":"527"},{"pid":"1631","uid":"527"},{"pid":"1631","uid":"527"},{"pid":"1631","uid":"527"},{"pid":"1631","uid":"527"},{"pid":"1631","uid":"527"},{"pid":"1631","uid":"527"},{"pid":"1631","uid":"527"},{"pid":"1631","uid":"527"},{"pid":"1631","uid":"527"},{"pid":"1631","uid":"527"},{"pid":"1631","uid":"527"},{"pid":"1631","uid":"527"},{"pid":"1631","uid":"527"},{"pid":"1631","uid":"527"},{"pid":"1631","uid":"527"},{"pid":"1631","uid":"527"},{"pid":"1631","uid":"527"},{"pid":"1631","uid":"527"},{"pid":"1631","uid":"527"},{"pid":"1631","uid":"527"},{"pid":"1631","uid":"527"},{"pid":"1631","uid":"527"},{"pid":"1631","uid":"527"},{"pid":"1631","uid":"527"},{"pid":"1631","uid":"527"},{"pid":"1631","uid":"527"},{"pid":"1631","uid":"527"},{"pid":"1631","uid":"527"},{"pid":"1631","uid":"527"},{"pid":"1631","uid":"527"},{"pid":"1631","uid":"527"},{"pid":"1631","uid":"527"},{"pid":"1631","uid":"527"},{"pid":"1631","uid":"527"},{"pid":"1631","uid":"527"},{"pid":"1631","uid":"527"},{"pid":"1631","uid":"527"},{"pid":"1631","uid":"527"},{"pid":"1631","uid":"527"},{"pid":"1631","uid":"527"},{"pid":"1631","uid":"527"},{"pid":"1631","uid":"527"},{"pid":"1631","uid":"527"},{"pid":"1631","uid":"527"},{"pid":"1631","uid":"527"},{"pid":"1631","uid":"527"},{"pid":"1631","uid":"527"},{"pid":"1631","uid":"527"},{"pid":"1631","uid":"527"},{"pid":"1631","uid":"527"},{"pid":"1631","uid":"527"},{"pid":"1631","uid":"527"},{"pid":"1631","uid":"527"},{"pid":"1631","uid":"527"},{"pid":"1631","uid":"527"},{"pid":"1631","uid":"527"},{"pid":"1631","uid":"527"},{"pid":"1631","uid":"527"},{"pid":"1631","uid":"527"},{"pid":"1631","uid":"527"},{"pid":"1631","uid":"527"},{"pid":"1631","uid":"527"},{"pid":"1631","uid":"527"},{"pid":"1631","uid":"527"},{"pid":"1631","uid":"527"},{"pid":"1631","uid":"527"},{"pid":"1631","uid":"527"},{"pid":"1631","uid":"527"},{"pid":"1631","uid":"527"},{"pid":"1631","uid":"527"},{"pid":"1631","uid":"527"},{"pid":"1631","uid":"527"},{"pid":"1631","uid":"527"},{"pid":"1631","uid":"527"},{"pid":"1631","uid":"527"},{"pid":"1631","uid":"527"},{"pid":"1631","uid":"527"},{"pid":"1631","uid":"527"},{"pid":"1631","uid":"527"},{"pid":"1631","uid":"527"},{"pid":"1631","uid":"527"},{"pid":"1631","uid":"527"},{"pid":"1631","uid":"527"},{"pid":"1631","uid":"527"},{"pid":"1631","uid":"527"},{"pid":"1631","uid":"527"},{"pid":"1631","uid":"527"},{"pid":"1631","uid":"527"},{"pid":"1631","uid":"527"},{"pid":"1631","uid":"527"},{"pid":"1631","uid":"527"},{"pid":"1631","uid":"527"},{"pid":"1631","uid":"527"},{"pid":"1631","uid":"527"},{"pid":"1631","uid":"527"},{"pid":"1631","uid":"527"},{"pid":"1631","uid":"527"},{"pid":"1631","uid":"527"},{"pid":"1631","uid":"527"},{"pid":"1631","uid":"527"},{"pid":"1631","uid":"527"},{"pid":"1631","uid":"527"},{"pid":"1631","uid":"527"},{"pid":"1631","uid":"527"},{"pid":"1631","uid":"527"},{"pid":"1631","uid":"527"},{"pid":"1631","uid":"527"},{"pid":"1631","uid":"527"},{"pid":"1631","uid":"527"},{"pid":"1631","uid":"527"},{"pid":"1631","uid":"527"},{"pid":"1631","uid":"527"},{"pid":"1631","uid":"527"},{"pid":"1631","uid":"527"},{"pid":"1631","uid":"527"},{"pid":"1631","uid":"527"},{"pid":"1631","uid":"527"},{"pid":"1631","uid":"527"},{"pid":"1631","uid":"527"},{"pid":"1631","uid":"527"},{"pid":"1631","uid":"527"},{"pid":"1631","uid":"527"},{"pid":"1631","uid":"527"},{"pid":"1631","uid":"527"},{"pid":"1631","uid":"527"},{"pid":"1631","uid":"527"},{"pid":"1631","uid":"527"},{"pid":"1631","uid":"527"},{"pid":"1631","uid":"527"},{"pid":"1631","uid":"527"},{"pid":"1631","uid":"527"},{"pid":"1631","uid":"527"},{"pid":"1631","uid":"527"},{"pid":"1631","uid":"527"},{"pid":"1631","uid":"527"},{"pid":"1631","uid":"527"},{"pid":"1631","uid":"527"},{"pid":"1631","uid":"527"},{"pid":"1631","uid":"527"},{"pid":"1631","uid":"527"},{"pid":"1631","uid":"527"},{"pid":"1631","uid":"527"},{"pid":"1631","uid":"527"},{"pid":"1631","uid":"527"},{"pid":"1631","uid":"527"},{"pid":"1631","uid":"527"},{"pid":"1631","uid":"527"},{"pid":"1631","uid":"527"},{"pid":"1631","uid":"527"},{"pid":"1631","uid":"527"},{"pid":"1631","uid":"527"},{"pid":"1631","uid":"527"},{"pid":"1631","uid":"527"},{"pid":"1631","uid":"527"},{"pid":"1631","uid":"527"},{"pid":"1631","uid":"527"},{"pid":"1631","uid":"527"},{"pid":"1631","uid":"527"},{"pid":"1631","uid":"527"},{"pid":"1631","uid":"527"},{"pid":"1631","uid":"527"},{"pid":"1631","uid":"527"},{"pid":"1631","uid":"527"},{"pid":"1631","uid":"527"},{"pid":"1631","uid":"527"},{"pid":"1631","uid":"527"},{"pid":"1631","uid":"527"},{"pid":"1631","uid":"527"},{"pid":"1631","uid":"527"},{"pid":"1631","uid":"527"},{"pid":"1631","uid":"527"},{"pid":"1631","uid":"527"},{"pid":"1631","uid":"527"},{"pid":"1631","uid":"527"},{"pid":"1631","uid":"527"},{"pid":"1631","uid":"527"},{"pid":"1631","uid":"527"},{"pid":"1631","uid":"527"},{"pid":"1631","uid":"527"},{"pid":"1631","uid":"527"},{"pid":"1631","uid":"527"},{"pid":"1631","uid":"527"},{"pid":"1631","uid":"527"},{"pid":"1631","uid":"527"},{"pid":"1631","uid":"527"},{"pid":"1631","uid":"527"},{"pid":"1631","uid":"527"},{"pid":"1631","uid":"527"},{"pid":"1631","uid":"527"},{"pid":"1631","uid":"527"},{"pid":"1631","uid":"527"},{"pid":"1631","uid":"527"},{"pid":"1631","uid":"527"},{"pid":"1631","uid":"527"},{"pid":"1631","uid":"527"},{"pid":"1631","uid":"527"},{"pid":"1631","uid":"527"},{"pid":"1631","uid":"527"},{"pid":"1631","uid":"527"},{"pid":"1631","uid":"527"},{"pid":"1631","uid":"527"},{"pid":"1631","uid":"527"},{"pid":"1631","uid":"527"},{"pid":"1631","uid":"527"},{"pid":"1631","uid":"527"},{"pid":"1631","uid":"527"},{"pid":"1631","uid":"527"},{"pid":"1631","uid":"527"},{"pid":"1631","uid":"527"},{"pid":"1631","uid":"527"},{"pid":"1631","uid":"527"},{"pid":"1631","uid":"527"},{"pid":"1631","uid":"527"},{"pid":"1631","uid":"527"},{"pid":"1631","uid":"527"},{"pid":"1631","uid":"527"},{"pid":"1631","uid":"527"},{"pid":"1631","uid":"527"},{"pid":"1631","uid":"527"},{"pid":"1631","uid":"527"},{"pid":"1631","uid":"527"},{"pid":"1631","uid":"527"},{"pid":"1631","uid":"527"},{"pid":"1631","uid":"527"},{"pid":"1631","uid":"527"},{"pid":"1631","uid":"527"},{"pid":"1631","uid":"527"},{"pid":"1631","uid":"527"},{"pid":"1631","uid":"527"},{"pid":"1631","uid":"527"},{"pid":"1631","uid":"527"},{"pid":"1631","uid":"527"},{"pid":"1631","uid":"527"},{"pid":"1631","uid":"527"},{"pid":"1631","uid":"527"},{"pid":"1631","uid":"527"},{"pid":"1631","uid":"527"},{"pid":"1631","uid":"527"},{"pid":"1631","uid":"527"},{"pid":"1631","uid":"527"},{"pid":"1631","uid":"527"},{"pid":"1631","uid":"527"},{"pid":"1631","uid":"527"},{"pid":"1631","uid":"527"},{"pid":"1631","uid":"527"},{"pid":"1631","uid":"527"},{"pid":"1631","uid":"527"},{"pid":"1631","uid":"527"},{"pid":"1631","uid":"527"},{"pid":"1631","uid":"527"},{"pid":"1631","uid":"527"},{"pid":"1631","uid":"527"},{"pid":"1631","uid":"527"},{"pid":"1631","uid":"527"},{"pid":"1631","uid":"527"},{"pid":"1631","uid":"527"},{"pid":"1631","uid":"527"},{"pid":"1631","uid":"527"},{"pid":"1631","uid":"527"},{"pid":"1631","uid":"527"},{"pid":"1631","uid":"527"},{"pid":"1631","uid":"527"},{"pid":"1631","uid":"527"},{"pid":"1631","uid":"527"},{"pid":"1631","uid":"527"},{"pid":"1631","uid":"527"},{"pid":"1631","uid":"527"},{"pid":"1631","uid":"527"},{"pid":"1631","uid":"527"},{"pid":"1631","uid":"527"},{"pid":"1631","uid":"527"},{"pid":"1631","uid":"527"},{"pid":"1631","uid":"527"},{"pid":"1631","uid":"527"},{"pid":"1631","uid":"527"},{"pid":"1631","uid":"527"},{"pid":"1631","uid":"527"},{"pid":"1631","uid":"527"},{"pid":"1631","uid":"527"},{"pid":"1631","uid":"527"},{"pid":"1631","uid":"527"},{"pid":"1631","uid":"527"},{"pid":"1631","uid":"527"},{"pid":"1631","uid":"527"},{"pid":"1631","uid":"527"},{"pid":"1631","uid":"527"},{"pid":"1631","uid":"527"},{"pid":"1631","uid":"527"},{"pid":"1631","uid":"527"},{"pid":"1631","uid":"527"},{"pid":"1631","uid":"527"},{"pid":"1631","uid":"527"},{"pid":"1631","uid":"527"},{"pid":"1631","uid":"527"},{"pid":"1631","uid":"527"},{"pid":"1631","uid":"527"},{"pid":"1631","uid":"527"},{"pid":"1631","uid":"527"},{"pid":"1631","uid":"527"},{"pid":"1631","uid":"527"},{"pid":"1631","uid":"527"},{"pid":"1631","uid":"527"},{"pid":"1631","uid":"527"},{"pid":"1631","uid":"527"},{"pid":"1631","uid":"527"},{"pid":"1631","uid":"527"},{"pid":"1631","uid":"527"},{"pid":"1631","uid":"527"},{"pid":"1631","uid":"527"},{"pid":"1631","uid":"527"},{"pid":"1631","uid":"527"},{"pid":"1631","uid":"527"},{"pid":"1631","uid":"527"},{"pid":"1631","uid":"527"},{"pid":"1631","uid":"527"},{"pid":"1631","uid":"527"},{"pid":"1631","uid":"527"},{"pid":"1631","uid":"527"},{"pid":"1631","uid":"527"},{"pid":"1631","uid":"527"},{"pid":"1631","uid":"527"},{"pid":"1631","uid":"527"},{"pid":"1631","uid":"527"},{"pid":"1631","uid":"527"},{"pid":"1631","uid":"527"},{"pid":"1631","uid":"527"},{"pid":"1631","uid":"527"},{"pid":"1631","uid":"527"},{"pid":"1631","uid":"527"},{"pid":"1631","uid":"527"},{"pid":"1631","uid":"527"},{"pid":"1631","uid":"527"},{"pid":"1631","uid":"527"},{"pid":"1631","uid":"527"},{"pid":"1631","uid":"527"},{"pid":"1631","uid":"527"},{"pid":"1631","uid":"527"},{"pid":"1631","uid":"527"},{"pid":"1631","uid":"527"},{"pid":"1631","uid":"527"},{"pid":"1631","uid":"527"},{"pid":"1631","uid":"527"},{"pid":"1631","uid":"527"},{"pid":"1631","uid":"527"},{"pid":"1631","uid":"527"},{"pid":"1631","uid":"527"},{"pid":"1631","uid":"527"},{"pid":"1631","uid":"527"},{"pid":"1631","uid":"527"},{"pid":"1631","uid":"527"},{"pid":"1631","uid":"527"},{"pid":"1631","uid":"527"},{"pid":"1631","uid":"527"},{"pid":"1631","uid":"527"},{"pid":"1631","uid":"527"},{"pid":"1631","uid":"527"},{"pid":"1631","uid":"527"},{"pid":"1631","uid":"527"},{"pid":"1631","uid":"527"},{"pid":"1631","uid":"527"}]